main.py
server_env_management-0.1.0.dist-info/METADATA
server_env_management-0.1.0.dist-info/WHEEL
server_env_management-0.1.0.dist-info/top_level.txt
server_env_management-0.1.0.dist-info/RECORD
