Metadata-Version: 2.1
Name: server-env-management
Version: 0.1.0
Summary: Add your description here
Requires-Python: >=3.8
Requires-Dist: docker >=7.1.0
Requires-Dist: pandas >=2.0.3
Requires-Dist: pyyaml >=6.0.2
Requires-Dist: textual >=0.73.0
Requires-Dist: textual-dev >=1.6.1
